ovos_audio2ipa_plugin_allosaurus/__init__.py
ovos_audio2ipa_plugin_allosaurus/version.py
ovos_audio2ipa_plugin_allosaurus-0.0.0a3.dist-info/LICENSE
ovos_audio2ipa_plugin_allosaurus-0.0.0a3.dist-info/METADATA
ovos_audio2ipa_plugin_allosaurus-0.0.0a3.dist-info/WHEEL
ovos_audio2ipa_plugin_allosaurus-0.0.0a3.dist-info/entry_points.txt
ovos_audio2ipa_plugin_allosaurus-0.0.0a3.dist-info/top_level.txt
ovos_audio2ipa_plugin_allosaurus-0.0.0a3.dist-info/zip-safe
ovos_audio2ipa_plugin_allosaurus-0.0.0a3.dist-info/RECORD
