Metadata-Version: 2.1
Name: ovos-audio2ipa-plugin-allosaurus
Version: 0.0.0a3
Summary: spoke lang detection framework
Home-page: https://github.com/OpenVoiceOS/ovos-audio2ipa-plugin-allosaurus
Author: JarbasAi
Author-email: jarbasai@mailfence.com
License: GPL3
Keywords: ovos OpenVoiceOS
Platform: UNKNOWN
Classifier: Development Status :: 3 - Alpha
Classifier: Intended Audience :: Developers
Classifier: Topic :: Text Processing :: Linguistic
Classifier: License :: OSI Approved :: Apache Software License
Classifier: Programming Language :: Python :: 2
Classifier: Programming Language :: Python :: 2.7
Classifier: Programming Language :: Python :: 3
Classifier: Programming Language :: Python :: 3.0
Classifier: Programming Language :: Python :: 3.1
Classifier: Programming Language :: Python :: 3.2
Classifier: Programming Language :: Python :: 3.3
Classifier: Programming Language :: Python :: 3.4
Classifier: Programming Language :: Python :: 3.5
Classifier: Programming Language :: Python :: 3.6
Requires-Dist: ovos-classifiers[sklearn] (>=0.0.0a1)
Requires-Dist: allosaurus
Requires-Dist: ovos-plugin-manager (>=0.0.23a11)
